libEscansion/__init__.py
libEscansion/libEscansion.py
libEscansion-1.1.0.dist-info/LICENSE
libEscansion-1.1.0.dist-info/METADATA
libEscansion-1.1.0.dist-info/WHEEL
libEscansion-1.1.0.dist-info/top_level.txt
libEscansion-1.1.0.dist-info/RECORD
