Metadata-Version: 2.1
Name: libEscansion
Version: 1.1.0
Summary: Metrical scansion for Spanish verses
Home-page: https://github.com/fsanzl/libEscansion
Author: Fernando Sanz-Lázaro
Author-email: fsanzl@gmail.com
License: LGPL
Project-URL: Source, https://github.com/fsanzl/libEscansion/
Project-URL: Tracker, https://github.com/fsanzl/libEscansion/issues
Classifier: License :: OSI Approved :: GNU Lesser General Public License v2 or later (LGPLv2+)
Classifier: Programming Language :: Python :: 3
Classifier: Programming Language :: Python :: 3.11
Classifier: Programming Language :: Python :: 3.10
Classifier: Programming Language :: Python :: 3.9
Classifier: Natural Language :: Spanish
Requires-Python: >=3.9
License-File: LICENSE
